Metadata-Version: 2.1
Name: sparkplusplus-cli
Version: 0.0.1.dev0
Summary: Awesome Cli for Developers
Home-page: https://github.com/sparkplusplus/sparkplusplus-cli
Download-URL: https://github.com/pateash/spp/archive/0.0.1-dev0.tar.gz
Author: Ashish Patel
Author-email: ashishpatel0720@gmail.com
License: MIT
Classifier: Development Status :: 3 - Alpha
Classifier: Intended Audience :: Developers
Classifier: Topic :: Software Development :: Libraries
Classifier: License :: OSI Approved :: MIT License
Classifier: Programming Language :: Python :: 3.9
Requires-Python: >=3.7
License-File: LICENSE
